vk/__init__.py
vk/api.py
vk/exceptions.py
vk/session.py
vk/utils.py
vk-3.0.dist-info/LICENSE
vk-3.0.dist-info/METADATA
vk-3.0.dist-info/WHEEL
vk-3.0.dist-info/top_level.txt
vk-3.0.dist-info/RECORD
