Metadata-Version: 2.1
Name: vk
Version: 3.0
Summary: Python vk.com API wrapper
Author-email: Dmitry Voronin <dimka665@gmail.com>
Maintainer-email: Yaroslav Kikel <yaroslav.kikel.06@inbox.ru>
License: MIT
Project-URL: Documentation, https://vk.readthedocs.io
Project-URL: Homepage, https://github.com/voronind/vk
Project-URL: Source, https://github.com/voronind/vk
Project-URL: Tracker, https://github.com/voronind/vk/issues
Keywords: vk.com,api,vk,wrappper
Classifier: Development Status :: 5 - Production/Stable
Classifier: Intended Audience :: Developers
Classifier: License :: OSI Approved :: MIT License
Classifier: Operating System :: OS Independent
Classifier: Programming Language :: Python
Classifier: Programming Language :: Python :: 3
Classifier: Programming Language :: Python :: 3 :: Only
Classifier: Programming Language :: Python :: 3.7
Classifier: Programming Language :: Python :: 3.8
Classifier: Programming Language :: Python :: 3.9
Classifier: Programming Language :: Python :: 3.10
Classifier: Programming Language :: Python :: Implementation :: CPython
Classifier: Programming Language :: Python :: Implementation :: PyPy
Classifier: Topic :: Software Development :: Libraries :: Python Modules
Provides-Extra: test
Provides-Extra: docs
License-File: LICENSE
